collective.abovecontentbodyportlets-1.0.0a2-py3.11-nspkg.pth
collective/abovecontentbodyportlets/__init__.py
collective/abovecontentbodyportlets/configure.zcml
collective/abovecontentbodyportlets/interfaces.py
collective/abovecontentbodyportlets/setuphandlers.py
collective/abovecontentbodyportlets/testing.py
collective/abovecontentbodyportlets/viewlet.pt
collective/abovecontentbodyportlets/viewlet.py
collective/abovecontentbodyportlets/locales/__init__.py
collective/abovecontentbodyportlets/locales/collective.abovecontentbodyportlets.pot
collective/abovecontentbodyportlets/locales/plone.pot
collective/abovecontentbodyportlets/locales/update.sh
collective/abovecontentbodyportlets/locales/en/LC_MESSAGES/plone.mo
collective/abovecontentbodyportlets/locales/en/LC_MESSAGES/plone.po
collective/abovecontentbodyportlets/locales/nl/LC_MESSAGES/collective.abovecontentbodyportlets.mo
collective/abovecontentbodyportlets/locales/nl/LC_MESSAGES/collective.abovecontentbodyportlets.po
collective/abovecontentbodyportlets/locales/nl/LC_MESSAGES/plone.mo
collective/abovecontentbodyportlets/locales/nl/LC_MESSAGES/plone.po
collective/abovecontentbodyportlets/profiles/default/browserlayer.xml
collective/abovecontentbodyportlets/profiles/default/metadata.xml
collective/abovecontentbodyportlets/profiles/default/portlets.xml
collective/abovecontentbodyportlets/profiles/uninstall/browserlayer.xml
collective/abovecontentbodyportlets/profiles/uninstall/portlets.xml
collective/abovecontentbodyportlets/tests/__init__.py
collective/abovecontentbodyportlets/tests/test_portlet_manager.py
collective/abovecontentbodyportlets/tests/test_setup.py
collective.abovecontentbodyportlets-1.0.0a2.dist-info/LICENSE.GPL
collective.abovecontentbodyportlets-1.0.0a2.dist-info/LICENSE.rst
collective.abovecontentbodyportlets-1.0.0a2.dist-info/METADATA
collective.abovecontentbodyportlets-1.0.0a2.dist-info/WHEEL
collective.abovecontentbodyportlets-1.0.0a2.dist-info/entry_points.txt
collective.abovecontentbodyportlets-1.0.0a2.dist-info/namespace_packages.txt
collective.abovecontentbodyportlets-1.0.0a2.dist-info/top_level.txt
collective.abovecontentbodyportlets-1.0.0a2.dist-info/RECORD
